{"legislative_session": "194th", "identifier": "H627", "title": "An Act relative to the strengthening of financial literacy throughout the commonwealth", "from_organization": "~{\"classification\": \"lower\"}", "classification": ["bill"], "subject": [], "abstracts": [{"note": "summary", "abstract": "By Representative Lawn of Watertown, a petition (accompanied by bill, House, No. 627) of John J. Lawn, Jr., for legislation to authorize the department of elementary and secondary education to establish the financial literacy trust fund.  Education."}], "other_titles": [], "other_identifiers": [], "actions": [{"description": "Referred to the committee on Education", "date": "2025-02-27", "organization_id": "~{\"classification\": \"lower\"}", "classification": ["referral-committee"], "related_entities": [{"name": "committee on Education", "entity_type": "organization", "organization_id": null}]}, {"description": "Senate concurred", "date": "2025-02-27", "organization_id": "~{\"classification\": \"upper\"}", "classification": [], "related_entities": []}], "sponsorships": [{"name": "John J. Lawn, Jr.", "classification": "primary", "entity_type": "person", "primary": true, "person_id": "~{\"name\": \"John J. Lawn, Jr.\"}", "organization_id": null}, {"name": "Bridget Plouffe", "classification": "cosponsor", "entity_type": "person", "primary": false, "person_id": "~{\"name\": \"Bridget Plouffe\"}", "organization_id": null}], "related_bills": [{"identifier": "HD 4074", "legislative_session": "194th", "relation_type": "replaces"}], "versions": [{"note": "Bill Text", "links": [{"url": "https://malegislature.gov/Bills/194/H627.pdf", "media_type": "application/pdf"}], "date": "", "classification": ""}], "documents": [], "citations": [], "sources": [{"url": "https://malegislature.gov/Bills/194/H627", "note": ""}], "extras": {}, "jurisdiction": {"id": "ocd-jurisdiction/country:us/state:ma/government", "name": "Massachusetts", "classification": "state", "division_id": "ocd-division/country:us/state:ma"}, "scraped_at": "2025-07-28T19:44:07+00:00", "_id": "395131c8-6beb-11f0-b36c-5a60dba6569e"}