{"legislative_session": "194th", "identifier": "HD4705", "title": "An Act relative to food dyes", "from_organization": "~{\"classification\": \"lower\"}", "classification": ["proposed bill"], "subject": [], "abstracts": [{"note": "summary", "abstract": "By Representative Howitt of Seekonk, a petition (subject to Joint Rule 12) of Steven S. Howitt relative to food dyes.  Public Health."}], "other_titles": [], "other_identifiers": [], "actions": [{"description": "Referred to the committee on House Rules", "date": "2025-05-19", "organization_id": "~{\"classification\": \"lower\"}", "classification": ["referral-committee"], "related_entities": [{"name": "committee on House Rules", "entity_type": "organization", "organization_id": null}]}], "sponsorships": [{"name": "Steven S. Howitt", "classification": "primary", "entity_type": "person", "primary": true, "person_id": "~{\"name\": \"Steven S. Howitt\"}", "organization_id": null}], "related_bills": [], "versions": [{"note": "Bill Text", "links": [{"url": "https://malegislature.gov/Bills/194/HD4705.pdf", "media_type": "application/pdf"}], "date": "", "classification": ""}], "documents": [], "citations": [], "sources": [{"url": "https://malegislature.gov/Bills/194/HD4705", "note": ""}], "extras": {}, "jurisdiction": {"id": "ocd-jurisdiction/country:us/state:ma/government", "name": "Massachusetts", "classification": "state", "division_id": "ocd-division/country:us/state:ma"}, "scraped_at": "2025-07-28T19:58:17+00:00", "_id": "3401e184-6bed-11f0-b36c-5a60dba6569e"}