{"legislative_session": "194th", "identifier": "HD4854", "title": "An Act authorizing the town of Billerica to transfer control of certain land of the town situated in the town of Billerica for recreational purposes for the purposes of constructing the Yankee Doodle Bike Path", "from_organization": "~{\"classification\": \"lower\"}", "classification": ["proposed bill"], "subject": [], "abstracts": [], "other_titles": [], "other_identifiers": [], "actions": [], "sponsorships": [{"name": "Marc T. Lombardo", "classification": "primary", "entity_type": "person", "primary": true, "person_id": "~{\"name\": \"Marc T. Lombardo\"}", "organization_id": null}, {"name": "Cindy F. Friedman", "classification": "cosponsor", "entity_type": "person", "primary": false, "person_id": "~{\"name\": \"Cindy F. Friedman\"}", "organization_id": null}], "related_bills": [], "versions": [{"note": "Bill Text", "links": [{"url": "https://malegislature.gov/Bills/194/HD4854.pdf", "media_type": "application/pdf"}], "date": "", "classification": ""}], "documents": [], "citations": [], "sources": [{"url": "https://malegislature.gov/Bills/194/HD4854", "note": ""}], "extras": {}, "jurisdiction": {"id": "ocd-jurisdiction/country:us/state:ma/government", "name": "Massachusetts", "classification": "state", "division_id": "ocd-division/country:us/state:ma"}, "scraped_at": "2025-07-28T20:02:43+00:00", "_id": "d266df14-6bed-11f0-b36c-5a60dba6569e"}