{
  "legislative_session": "194th",
  "identifier": "S2648",
  "title": "An Act changing the board of selectmen in the town of Boylston to select board",
  "from_organization": "~{\"classification\": \"upper\"}",
  "classification": [
    "bill"
  ],
  "subject": [],
  "abstracts": [
    {
      "note": "summary",
      "abstract": "By Ms. Kennedy and Ms. Kilcoyne of Worcester, a joint petition (accompanied by bill, Senate, No. 2628) of Robyn K. Kennedy and Meghan K. Kilcoyne (by vote of the town) for legislation relative to the select board of the town of Boylston.  Municipalities and Regional Government.  [Local Approval Received.]"
    }
  ],
  "other_titles": [],
  "other_identifiers": [],
  "actions": [
    {
      "description": "Referred to the committee on Municipalities and Regional Government",
      "date": "2025-10-14",
      "organization_id": "~{\"classification\": \"upper\"}",
      "classification": [
        "referral-committee"
      ],
      "related_entities": [
        {
          "name": "committee on Municipalities and Regional Government",
          "entity_type": "organization",
          "organization_id": null
        }
      ],
      "_processing": {
        "log_file_created": "2025-10-26T04:18:38Z"
      }
    },
    {
      "description": "House concurred",
      "date": "2025-10-15",
      "organization_id": "~{\"classification\": \"lower\"}",
      "classification": [],
      "related_entities": [],
      "_processing": {
        "log_file_created": "2025-10-26T04:18:38Z"
      }
    }
  ],
  "sponsorships": [
    {
      "name": "Robyn K. Kennedy",
      "classification": "cosponsor",
      "entity_type": "person",
      "primary": false,
      "person_id": "~{\"name\": \"Robyn K. Kennedy\"}",
      "organization_id": null
    },
    {
      "name": "Meghan K. Kilcoyne",
      "classification": "cosponsor",
      "entity_type": "person",
      "primary": false,
      "person_id": "~{\"name\": \"Meghan K. Kilcoyne\"}",
      "organization_id": null
    }
  ],
  "related_bills": [
    {
      "identifier": "SD 3284",
      "legislative_session": "194th",
      "relation_type": "replaces"
    }
  ],
  "versions": [
    {
      "note": "Bill Text",
      "links": [
        {
          "url": "https://malegislature.gov/Bills/194/S2648.pdf",
          "media_type": "application/pdf"
        }
      ],
      "date": "",
      "classification": ""
    }
  ],
  "documents": [],
  "citations": [],
  "sources": [
    {
      "url": "https://malegislature.gov/Bills/194/S2648",
      "note": ""
    }
  ],
  "extras": {},
  "jurisdiction": {
    "id": "ocd-jurisdiction/country:us/state:ma/government",
    "name": "Massachusetts",
    "classification": "state",
    "division_id": "ocd-division/country:us/state:ma"
  },
  "_processing": {
    "logs_latest_update": "2025-10-26T04:18:38Z"
  }
}