{
  "legislative_session": "194th",
  "identifier": "H1133",
  "title": "An Act relative to patient financial protection",
  "from_organization": "~{\"classification\": \"lower\"}",
  "classification": [
    "bill"
  ],
  "subject": [],
  "abstracts": [
    {
      "note": "summary",
      "abstract": "By Representative Decker of Cambridge, a petition (accompanied by bill, House, No. 1133) of Marjorie C. Decker relative to insurance coverage out-of-pocket limits for prescription drugs.  Financial Services."
    }
  ],
  "other_titles": [],
  "other_identifiers": [],
  "actions": [
    {
      "description": "Referred to the committee on Financial Services",
      "date": "2025-02-27",
      "organization_id": "~{\"classification\": \"lower\"}",
      "classification": [
        "referral-committee"
      ],
      "related_entities": [
        {
          "name": "committee on Financial Services",
          "entity_type": "organization",
          "organization_id": null
        }
      ],
      "_processing": {
        "log_file_created": "2025-10-26T04:18:33Z"
      }
    },
    {
      "description": "Senate concurred",
      "date": "2025-02-27",
      "organization_id": "~{\"classification\": \"upper\"}",
      "classification": [],
      "related_entities": [],
      "_processing": {
        "log_file_created": "2025-10-26T04:18:33Z"
      }
    },
    {
      "description": "Hearing scheduled for 06/10/2025 from 10:30 AM-01:00 PM in A-2",
      "date": "2025-06-03",
      "organization_id": "~{\"classification\": \"legislature\"}",
      "classification": [],
      "related_entities": [],
      "_processing": {
        "log_file_created": "2025-10-26T04:18:33Z"
      }
    },
    {
      "description": "Accompanied a new draft, see H4492",
      "date": "2025-09-18",
      "organization_id": "~{\"classification\": \"lower\"}",
      "classification": [],
      "related_entities": [],
      "_processing": {
        "log_file_created": "2025-10-26T04:18:33Z"
      }
    }
  ],
  "sponsorships": [
    {
      "name": "Marjorie C. Decker",
      "classification": "primary",
      "entity_type": "person",
      "primary": true,
      "person_id": "~{\"name\": \"Marjorie C. Decker\"}",
      "organization_id": null
    },
    {
      "name": "Estela A. Reyes",
      "classification": "cosponsor",
      "entity_type": "person",
      "primary": false,
      "person_id": "~{\"name\": \"Estela A. Reyes\"}",
      "organization_id": null
    }
  ],
  "related_bills": [
    {
      "identifier": "HD 3236",
      "legislative_session": "194th",
      "relation_type": "replaces"
    }
  ],
  "versions": [
    {
      "note": "Bill Text",
      "links": [
        {
          "url": "https://malegislature.gov/Bills/194/H1133.pdf",
          "media_type": "application/pdf"
        }
      ],
      "date": "",
      "classification": ""
    }
  ],
  "documents": [],
  "citations": [],
  "sources": [
    {
      "url": "https://malegislature.gov/Bills/194/H1133",
      "note": ""
    }
  ],
  "extras": {},
  "jurisdiction": {
    "id": "ocd-jurisdiction/country:us/state:ma/government",
    "name": "Massachusetts",
    "classification": "state",
    "division_id": "ocd-division/country:us/state:ma"
  },
  "_processing": {
    "logs_latest_update": "2025-10-26T04:18:33Z"
  }
}