{
  "legislative_session": "194th",
  "identifier": "SD2783",
  "title": "DTA 2-Gen Economic Mobility Grant FY24 Report",
  "from_organization": "~{\"classification\": \"upper\"}",
  "classification": [
    "proposed bill"
  ],
  "subject": [],
  "abstracts": [
    {
      "note": "summary",
      "abstract": "Report of the Department of Transitional Assistance (pursuant to line item 4401-1003 of Section 2 of Chapter 140 of the Acts 2024) submitting its 2-Gen Economic Mobility Programs  FY24 report"
    }
  ],
  "other_titles": [],
  "other_identifiers": [],
  "actions": [
    {
      "description": "Placed on file",
      "date": "2025-03-27",
      "organization_id": "~{\"classification\": \"upper\"}",
      "classification": [],
      "related_entities": [],
      "_processing": {
        "log_file_created": "2025-10-26T04:18:38Z"
      }
    }
  ],
  "sponsorships": [
    {
      "name": "Department of Transitional Assistance",
      "classification": "primary",
      "entity_type": "organization",
      "primary": true,
      "person_id": null,
      "organization_id": "~{\"name\": \"Department of Transitional Assistance\"}"
    }
  ],
  "related_bills": [],
  "versions": [
    {
      "note": "Bill Text",
      "links": [
        {
          "url": "https://malegislature.gov/Bills/194/SD2783.pdf",
          "media_type": "application/pdf"
        }
      ],
      "date": "",
      "classification": ""
    }
  ],
  "documents": [],
  "citations": [],
  "sources": [
    {
      "url": "https://malegislature.gov/Bills/194/SD2783",
      "note": ""
    }
  ],
  "extras": {},
  "jurisdiction": {
    "id": "ocd-jurisdiction/country:us/state:ma/government",
    "name": "Massachusetts",
    "classification": "state",
    "division_id": "ocd-division/country:us/state:ma"
  },
  "_processing": {
    "logs_latest_update": "2025-10-26T04:18:38Z"
  }
}