{
  "legislative_session": "194th",
  "identifier": "SD2877",
  "title": "Residential Assistance for Families in Transition (RAFT) FY25 Q3 Report",
  "from_organization": "~{\"classification\": \"upper\"}",
  "classification": [
    "proposed bill"
  ],
  "subject": [],
  "abstracts": [
    {
      "note": "summary",
      "abstract": "Report of Executive Office of Housing and Livable Communities (pursuant to line item 7004-9316 of Section 2 of Chapter 140 of the Acts of 2024) submitting it Residential Assistance for Families in Transition (RAFT) program third quarter report"
    }
  ],
  "other_titles": [],
  "other_identifiers": [],
  "actions": [
    {
      "description": "Placed on file",
      "date": "2025-05-29",
      "organization_id": "~{\"classification\": \"upper\"}",
      "classification": [],
      "related_entities": [],
      "_processing": {
        "log_file_created": "2025-10-26T04:18:35Z"
      }
    }
  ],
  "sponsorships": [
    {
      "name": "Executive Office of Housing and Livable Communities",
      "classification": "primary",
      "entity_type": "organization",
      "primary": true,
      "person_id": null,
      "organization_id": "~{\"name\": \"Executive Office of Housing and Livable Communities\"}"
    }
  ],
  "related_bills": [],
  "versions": [
    {
      "note": "Bill Text",
      "links": [
        {
          "url": "https://malegislature.gov/Bills/194/SD2877.pdf",
          "media_type": "application/pdf"
        }
      ],
      "date": "",
      "classification": ""
    }
  ],
  "documents": [],
  "citations": [],
  "sources": [
    {
      "url": "https://malegislature.gov/Bills/194/SD2877",
      "note": ""
    }
  ],
  "extras": {},
  "jurisdiction": {
    "id": "ocd-jurisdiction/country:us/state:ma/government",
    "name": "Massachusetts",
    "classification": "state",
    "division_id": "ocd-division/country:us/state:ma"
  },
  "_processing": {
    "logs_latest_update": "2025-10-26T04:18:35Z",
    "text_extraction_latest_update": "2025-10-26T05:45:14.668247Z"
  }
}