{
  "legislative_session": "194th",
  "identifier": "HD4720",
  "title": "A communication from the Office of the State Auditor (see item 0710-0200 of Section 2 of Chapter 140 of the Acts of 2024) submitting its third quarter fiscal year 2025 report of the Bureau of Special Investigations from January 1, 2025 to March 31, 2025",
  "from_organization": "~{\"classification\": \"lower\"}",
  "classification": [
    "proposed bill"
  ],
  "subject": [],
  "abstracts": [],
  "other_titles": [],
  "other_identifiers": [],
  "actions": [
    {
      "description": "Placed on file",
      "date": "2025-05-29",
      "organization_id": "~{\"classification\": \"lower\"}",
      "classification": [],
      "related_entities": [],
      "_processing": {
        "log_file_created": "2025-10-26T04:18:37Z"
      }
    }
  ],
  "sponsorships": [
    {
      "name": "Auditor of the Commonwealth",
      "classification": "primary",
      "entity_type": "organization",
      "primary": true,
      "person_id": null,
      "organization_id": "~{\"name\": \"Auditor of the Commonwealth\"}"
    }
  ],
  "related_bills": [],
  "versions": [
    {
      "note": "Bill Text",
      "links": [
        {
          "url": "https://malegislature.gov/Bills/194/HD4720.pdf",
          "media_type": "application/pdf"
        }
      ],
      "date": "",
      "classification": ""
    }
  ],
  "documents": [],
  "citations": [],
  "sources": [
    {
      "url": "https://malegislature.gov/Bills/194/HD4720",
      "note": ""
    }
  ],
  "extras": {},
  "jurisdiction": {
    "id": "ocd-jurisdiction/country:us/state:ma/government",
    "name": "Massachusetts",
    "classification": "state",
    "division_id": "ocd-division/country:us/state:ma"
  },
  "_processing": {
    "logs_latest_update": "2025-10-26T04:18:37Z"
  }
}