{
  "legislative_session": "194th",
  "identifier": "H4612",
  "title": "An Act relative to the creation of an endometriosis task force",
  "from_organization": "~{\"classification\": \"lower\"}",
  "classification": [
    "bill"
  ],
  "subject": [],
  "abstracts": [],
  "other_titles": [],
  "other_identifiers": [],
  "actions": [
    {
      "description": "Reported from the committee on Public Health",
      "date": "2025-10-20",
      "organization_id": "~{\"classification\": \"lower\"}",
      "classification": [],
      "related_entities": [],
      "_processing": {
        "log_file_created": "2025-10-26T04:18:36Z"
      }
    },
    {
      "description": "New draft of H2527",
      "date": "2025-10-20",
      "organization_id": "~{\"classification\": \"lower\"}",
      "classification": [],
      "related_entities": [],
      "_processing": {
        "log_file_created": "2025-10-26T04:18:36Z"
      }
    },
    {
      "description": "Bill reported favorably by committee and referred to the committee on House Ways and Means",
      "date": "2025-10-20",
      "organization_id": "~{\"classification\": \"lower\"}",
      "classification": [
        "committee-passage-favorable",
        "referral-committee"
      ],
      "related_entities": [
        {
          "name": "the committee on House Ways and Means",
          "entity_type": "organization",
          "organization_id": null
        },
        {
          "name": "committee on House Ways and Means",
          "entity_type": "organization",
          "organization_id": null
        }
      ],
      "_processing": {
        "log_file_created": "2025-10-26T04:18:36Z"
      }
    }
  ],
  "sponsorships": [
    {
      "name": "Joint Committee on Public Health",
      "classification": "primary",
      "entity_type": "organization",
      "primary": true,
      "person_id": null,
      "organization_id": "~{\"name\": \"Joint Committee on Public Health\"}"
    },
    {
      "name": "Lindsay N. Sabadosa",
      "classification": "cosponsor",
      "entity_type": "person",
      "primary": false,
      "person_id": "~{\"name\": \"Lindsay N. Sabadosa\"}",
      "organization_id": null
    },
    {
      "name": "Christopher Hendricks",
      "classification": "cosponsor",
      "entity_type": "person",
      "primary": false,
      "person_id": "~{\"name\": \"Christopher Hendricks\"}",
      "organization_id": null
    },
    {
      "name": "Jason M. Lewis",
      "classification": "cosponsor",
      "entity_type": "person",
      "primary": false,
      "person_id": "~{\"name\": \"Jason M. Lewis\"}",
      "organization_id": null
    },
    {
      "name": "Hannah Kane",
      "classification": "cosponsor",
      "entity_type": "person",
      "primary": false,
      "person_id": "~{\"name\": \"Hannah Kane\"}",
      "organization_id": null
    },
    {
      "name": "Priscila S. Sousa",
      "classification": "cosponsor",
      "entity_type": "person",
      "primary": false,
      "person_id": "~{\"name\": \"Priscila S. Sousa\"}",
      "organization_id": null
    },
    {
      "name": "Natalie M. Higgins",
      "classification": "cosponsor",
      "entity_type": "person",
      "primary": false,
      "person_id": "~{\"name\": \"Natalie M. Higgins\"}",
      "organization_id": null
    },
    {
      "name": "Thomas W. Moakley",
      "classification": "cosponsor",
      "entity_type": "person",
      "primary": false,
      "person_id": "~{\"name\": \"Thomas W. Moakley\"}",
      "organization_id": null
    },
    {
      "name": "Rodney M. Elliott",
      "classification": "cosponsor",
      "entity_type": "person",
      "primary": false,
      "person_id": "~{\"name\": \"Rodney M. Elliott\"}",
      "organization_id": null
    },
    {
      "name": "Sean Garballey",
      "classification": "cosponsor",
      "entity_type": "person",
      "primary": false,
      "person_id": "~{\"name\": \"Sean Garballey\"}",
      "organization_id": null
    },
    {
      "name": "Kristin E. Kassner",
      "classification": "cosponsor",
      "entity_type": "person",
      "primary": false,
      "person_id": "~{\"name\": \"Kristin E. Kassner\"}",
      "organization_id": null
    },
    {
      "name": "Homar G\u00f3mez",
      "classification": "cosponsor",
      "entity_type": "person",
      "primary": false,
      "person_id": "~{\"name\": \"Homar G\\u00f3mez\"}",
      "organization_id": null
    },
    {
      "name": "Manny Cruz",
      "classification": "cosponsor",
      "entity_type": "person",
      "primary": false,
      "person_id": "~{\"name\": \"Manny Cruz\"}",
      "organization_id": null
    },
    {
      "name": "Steven Owens",
      "classification": "cosponsor",
      "entity_type": "person",
      "primary": false,
      "person_id": "~{\"name\": \"Steven Owens\"}",
      "organization_id": null
    },
    {
      "name": "Bradley H. Jones, Jr.",
      "classification": "cosponsor",
      "entity_type": "person",
      "primary": false,
      "person_id": "~{\"name\": \"Bradley H. Jones, Jr.\"}",
      "organization_id": null
    },
    {
      "name": "Bud L. Williams",
      "classification": "cosponsor",
      "entity_type": "person",
      "primary": false,
      "person_id": "~{\"name\": \"Bud L. Williams\"}",
      "organization_id": null
    },
    {
      "name": "Vanna Howard",
      "classification": "cosponsor",
      "entity_type": "person",
      "primary": false,
      "person_id": "~{\"name\": \"Vanna Howard\"}",
      "organization_id": null
    },
    {
      "name": "Judith A. Garcia",
      "classification": "cosponsor",
      "entity_type": "person",
      "primary": false,
      "person_id": "~{\"name\": \"Judith A. Garcia\"}",
      "organization_id": null
    },
    {
      "name": "Brian M. Ashe",
      "classification": "cosponsor",
      "entity_type": "person",
      "primary": false,
      "person_id": "~{\"name\": \"Brian M. Ashe\"}",
      "organization_id": null
    },
    {
      "name": "Thomas P. Walsh",
      "classification": "cosponsor",
      "entity_type": "person",
      "primary": false,
      "person_id": "~{\"name\": \"Thomas P. Walsh\"}",
      "organization_id": null
    },
    {
      "name": "Margaret R. Scarsdale",
      "classification": "cosponsor",
      "entity_type": "person",
      "primary": false,
      "person_id": "~{\"name\": \"Margaret R. Scarsdale\"}",
      "organization_id": null
    },
    {
      "name": "Shirley B. Arriaga",
      "classification": "cosponsor",
      "entity_type": "person",
      "primary": false,
      "person_id": "~{\"name\": \"Shirley B. Arriaga\"}",
      "organization_id": null
    },
    {
      "name": "Christine P. Barber",
      "classification": "cosponsor",
      "entity_type": "person",
      "primary": false,
      "person_id": "~{\"name\": \"Christine P. Barber\"}",
      "organization_id": null
    },
    {
      "name": "Amy Mah Sangiolo",
      "classification": "cosponsor",
      "entity_type": "person",
      "primary": false,
      "person_id": "~{\"name\": \"Amy Mah Sangiolo\"}",
      "organization_id": null
    }
  ],
  "related_bills": [],
  "versions": [
    {
      "note": "Bill Text",
      "links": [
        {
          "url": "https://malegislature.gov/Bills/194/H4612.pdf",
          "media_type": "application/pdf"
        }
      ],
      "date": "",
      "classification": ""
    }
  ],
  "documents": [],
  "citations": [],
  "sources": [
    {
      "url": "https://malegislature.gov/Bills/194/H4612",
      "note": ""
    }
  ],
  "extras": {},
  "jurisdiction": {
    "id": "ocd-jurisdiction/country:us/state:ma/government",
    "name": "Massachusetts",
    "classification": "state",
    "division_id": "ocd-division/country:us/state:ma"
  },
  "_processing": {
    "logs_latest_update": "2025-10-26T04:18:36Z"
  }
}