{
  "legislative_session": "194th",
  "identifier": "H1028",
  "title": "An Act relative to the protection of our drinking water from nitrosodimethylamine",
  "from_organization": "~{\"classification\": \"lower\"}",
  "classification": [
    "bill"
  ],
  "subject": [],
  "abstracts": [
    {
      "note": "summary",
      "abstract": "By Representative Robertson of Tewksbury, a petition (accompanied by bill, House, No. 1028) of David Allen Robertson relative to maximum containment levels for certain harmful compounds in drinking water.  Environment and Natural Resources."
    }
  ],
  "other_titles": [],
  "other_identifiers": [],
  "actions": [
    {
      "description": "Referred to the committee on Environment and Natural Resources",
      "date": "2025-02-27",
      "organization_id": "~{\"classification\": \"lower\"}",
      "classification": [
        "referral-committee"
      ],
      "related_entities": [
        {
          "name": "committee on Environment and Natural Resources",
          "entity_type": "organization",
          "organization_id": null
        }
      ],
      "_processing": {
        "log_file_created": "2025-10-26T04:18:39Z"
      }
    },
    {
      "description": "Senate concurred",
      "date": "2025-02-27",
      "organization_id": "~{\"classification\": \"upper\"}",
      "classification": [],
      "related_entities": [],
      "_processing": {
        "log_file_created": "2025-10-26T04:18:39Z"
      }
    },
    {
      "description": "Hearing scheduled for 06/03/2025 from 01:00 PM-05:00 PM in A-1",
      "date": "2025-05-21",
      "organization_id": "~{\"classification\": \"legislature\"}",
      "classification": [],
      "related_entities": [],
      "_processing": {
        "log_file_created": "2025-10-26T04:18:39Z"
      }
    },
    {
      "description": "Reporting date extended to Wednesday, December 31, 2025",
      "date": "2025-08-28",
      "organization_id": "~{\"classification\": \"lower\"}",
      "classification": [],
      "related_entities": [],
      "_processing": {
        "log_file_created": "2025-10-26T04:18:39Z"
      }
    }
  ],
  "sponsorships": [
    {
      "name": "David Allen Robertson",
      "classification": "primary",
      "entity_type": "person",
      "primary": true,
      "person_id": "~{\"name\": \"David Allen Robertson\"}",
      "organization_id": null
    }
  ],
  "related_bills": [
    {
      "identifier": "HD 3195",
      "legislative_session": "194th",
      "relation_type": "replaces"
    }
  ],
  "versions": [
    {
      "note": "Bill Text",
      "links": [
        {
          "url": "https://malegislature.gov/Bills/194/H1028.pdf",
          "media_type": "application/pdf"
        }
      ],
      "date": "",
      "classification": ""
    }
  ],
  "documents": [],
  "citations": [],
  "sources": [
    {
      "url": "https://malegislature.gov/Bills/194/H1028",
      "note": ""
    }
  ],
  "extras": {},
  "jurisdiction": {
    "id": "ocd-jurisdiction/country:us/state:ma/government",
    "name": "Massachusetts",
    "classification": "state",
    "division_id": "ocd-division/country:us/state:ma"
  },
  "_processing": {
    "logs_latest_update": "2025-10-26T04:18:39Z",
    "text_extraction_latest_update": "2025-10-26T04:49:52.544541Z"
  }
}